artemis7/__init__.py
artemis7/datagenerator/__init__.py
artemis7/datagenerator/virtual_drift_generator.py
artemis7/myplot/MyPlot.py
artemis7/myplot/__init__.py
artemis7/myplot/_myplot.py
artemis7/stats/__init__.py
artemis7/stats/_binning.py
artemis7/stats/_fid.py
artemis7/stats/_multivariate_sampling.py
artemis7/stats/_piecewise_rejection_sampling.py
artemis7/stats/_population_stability_index.py
artemis7/stats/binning.py
artemis7/stats/frechet_inception_distance.py
artemis7/stats/multivariate_sampling.py
artemis7/stats/piecewise_rejection_sampling.py
artemis7/stats/population_stability_index.py
artemis7/util/__init__.py
artemis7/util/_colorprint.py
artemis7/util/_function_list.py
artemis7/util/_make_movie.py
artemis7/util/_progressbar.py
artemis7/util/colorprint.py
artemis7/util/function_list.py
artemis7/util/make_movie.py
artemis7/util/progressbar.py
artemis7-0.0.4.dist-info/METADATA
artemis7-0.0.4.dist-info/WHEEL
artemis7-0.0.4.dist-info/top_level.txt
artemis7-0.0.4.dist-info/RECORD
