Metadata-Version: 2.1
Name: artemis7
Version: 0.0.4
Summary: Personal library to compute and draw
Home-page: https://github.com/dowoonlee/artemis.git
Author: dwlee
Author-email: dwlee717@gmail.com
License: artemis7
Requires-Dist: numpy ==1.22.3
Requires-Dist: matplotlib ==3.5.2
Requires-Dist: astropy ==5.1
Requires-Dist: scipy ==1.7.3
Requires-Dist: pandas ==1.4.3
Requires-Dist: imageio ==2.19.3
